html_report_line_profiler/__init__.py
html_report_line_profiler/__version__.py
html_report_line_profiler/unittest_ext_profiler.py
html_report_line_profiler/generate_html_report/__init__.py
html_report_line_profiler/generate_html_report/_extract_profiled_data.py
html_report_line_profiler/generate_html_report/_extract_tools.py
html_report_line_profiler/generate_html_report/_extract_with_mask.py
html_report_line_profiler/generate_html_report/_find_profiled_files.py
html_report_line_profiler/generate_html_report/_find_test_functions.py
html_report_line_profiler/generate_html_report/_generate_html_page.py
html_report_line_profiler/generate_html_report/_generate_page_index.py
html_report_line_profiler/generate_html_report/_generate_tools.py
html_report_line_profiler/generate_html_report/_profilefile2htmlfile.py
html_report_line_profiler/generate_html_report/_tool_find.py
html_report_line_profiler/generate_html_report/_tools_profile.py
html_report_line_profiler/generate_html_report/generate_html_report_fct.py
html_report_line_profiler/generate_html_report/template/page.html
html_report_line_profiler/generate_html_report/template/style.css
html_report_line_profiler-0.1.1.data/scripts/profiler_html_report.py
html_report_line_profiler-0.1.1.dist-info/METADATA
html_report_line_profiler-0.1.1.dist-info/WHEEL
html_report_line_profiler-0.1.1.dist-info/top_level.txt
html_report_line_profiler-0.1.1.dist-info/RECORD
