Metadata-Version: 2.1
Name: html-report-line-profiler
Version: 0.1.1
Summary: Generate an HTML report for line_parser
Home-page: https://1sixunhuit.frama.io/html_report_line_profiler
Author: Pierre
Author-email: pierre@exemple.com
License: AGPL 3
Keywords: ['profiling','profiler','line_profiler','html','report']
Classifier: Development Status :: 3 - Alpha
Classifier: Intended Audience :: Developers
Classifier: Programming Language :: Python :: 3.9
Classifier: Environment :: Console
Classifier: Operating System :: POSIX :: Linux
Classifier: Natural Language :: French
Classifier: Natural Language :: English
Classifier: License :: OSI Approved :: GNU Affero General Public License v3
Classifier: Operating System :: OS Independent
Requires-Python: >=3.9, <4
Requires-Dist: line-profiler (==4.0.3)
Provides-Extra: doc
Requires-Dist: sphinx (==6.2.1) ; extra == 'doc'
Requires-Dist: sphinx-rtd-theme (==1.2.1) ; extra == 'doc'
Requires-Dist: myst-parser (==1.0.0) ; extra == 'doc'
Provides-Extra: test
Requires-Dist: coverage (==7.2.7) ; extra == 'test'
Requires-Dist: flake8 (==6.0.0) ; extra == 'test'
Requires-Dist: flake8-html (==0.4.3) ; extra == 'test'
Provides-Extra: upload
Requires-Dist: twine (==4.0.2) ; extra == 'upload'
Requires-Dist: wheel (==0.40.0) ; extra == 'upload'
